slapos.core-1.16.3-py3.11-nspkg.pth
slapos/README.console.rst
slapos/README.format.rst
slapos/README.grid.rst
slapos/README.manager.rst
slapos/README.proxy.rst
slapos/README.slap.rst
slapos/bang.py
slapos/client.py
slapos/format.py
slapos/human.py
slapos/slapos-client.cfg.example
slapos/slapos-proxy.cfg.example
slapos/slapos.cfg.example
slapos/slapos.xsd
slapos/util.py
slapos/version.py
slapos/cli/__init__.py
slapos/cli/bang.py
slapos/cli/boot.py
slapos/cli/cache_binarysr.py
slapos/cli/cache_pypi.py
slapos/cli/cache_url.py
slapos/cli/collect.py
slapos/cli/command.py
slapos/cli/complete.py
slapos/cli/computer_info.py
slapos/cli/computer_list.py
slapos/cli/computer_token.py
slapos/cli/config.py
slapos/cli/configure_client.py
slapos/cli/console.py
slapos/cli/entry.py
slapos/cli/format.py
slapos/cli/info.py
slapos/cli/list.py
slapos/cli/proxy_show.py
slapos/cli/proxy_start.py
slapos/cli/prune.py
slapos/cli/register.py
slapos/cli/remove.py
slapos/cli/request.py
slapos/cli/slapgrid.py
slapos/cli/supervisorctl.py
slapos/cli/supervisord.py
slapos/cli/supply.py
slapos/cli/coloredlogs/LICENSE.txt
slapos/cli/coloredlogs/README.rst
slapos/cli/coloredlogs/__init__.py
slapos/cli/coloredlogs/converter.py
slapos/cli/coloredlogs/demo.py
slapos/cli/configure_local/__init__.py
slapos/collect/README.txt
slapos/collect/__init__.py
slapos/collect/db.py
slapos/collect/entity.py
slapos/collect/reporter.py
slapos/collect/snapshot.py
slapos/collect/temperature/__init__.py
slapos/collect/temperature/heating.py
slapos/grid/SlapObject.py
slapos/grid/__init__.py
slapos/grid/distribution.py
slapos/grid/exception.py
slapos/grid/networkcache.py
slapos/grid/py.typed
slapos/grid/slapgrid.py
slapos/grid/svcbackend.py
slapos/grid/utils.py
slapos/grid/watchdog.py
slapos/grid/zc.buildout-bootstrap.py
slapos/grid/promise/__init__.py
slapos/grid/promise/generic.py
slapos/grid/promise/interface.py
slapos/grid/promise/runpromises.py
slapos/grid/promise/wrapper.py
slapos/grid/templates/buildout-tail.cfg.in
slapos_core-1.16.3.dist-info/METADATA
slapos_core-1.16.3.dist-info/WHEEL
slapos_core-1.16.3.dist-info/entry_points.txt
slapos_core-1.16.3.dist-info/namespace_packages.txt
slapos_core-1.16.3.dist-info/top_level.txt
slapos_core-1.16.3.dist-info/RECORD
