Metadata-Version: 2.4
Name: slapos.core
Version: 1.16.3
Summary: SlapOS core.
Home-page: https://slapos.nexedi.com/
Author: VIFIB
License: GPLv3
Keywords: slapos core
Classifier: Programming Language :: Python
Requires-Dist: Flask>=1.1.2
Requires-Dist: lxml
Requires-Dist: netaddr>=0.7.5
Requires-Dist: netifaces
Requires-Dist: setuptools
Requires-Dist: supervisor
Requires-Dist: psutil>=2.0.0
Requires-Dist: xml_marshaller>=0.9.3
Requires-Dist: zope.interface
Requires-Dist: zc.buildout
Requires-Dist: cliff
Requires-Dist: requests>=2.4.3
Requires-Dist: six
Requires-Dist: cachecontrol[filecache]
Requires-Dist: jsonschema
Requires-Dist: PyYAML
Requires-Dist: uritemplate
Requires-Dist: distro
Requires-Dist: subprocess32; python_version < "3"
Requires-Dist: enum34; python_version < "3"
Requires-Dist: selectors34; python_version < "3"
Requires-Dist: ipaddress; python_version < "3"
Provides-Extra: docs
Requires-Dist: Sphinx; extra == "docs"
Requires-Dist: repoze.sphinx.autointerface; extra == "docs"
Requires-Dist: sphinxcontrib.programoutput; extra == "docs"
Provides-Extra: ipython-console
Requires-Dist: ipython; extra == "ipython-console"
Provides-Extra: bpython-console
Requires-Dist: bpython; extra == "bpython-console"
Provides-Extra: test
Requires-Dist: pyflakes; extra == "test"
Requires-Dist: mock; extra == "test"
Requires-Dist: httmock; extra == "test"
Provides-Extra: testing
Requires-Dist: caucase; extra == "testing"
Requires-Dist: cryptography; extra == "testing"
Dynamic: author
Dynamic: classifier
Dynamic: description
Dynamic: home-page
Dynamic: keywords
Dynamic: license
Dynamic: provides-extra
Dynamic: requires-dist
Dynamic: summary
